Workbook

Sheet 1
B2: Payment Certificate
B4: Company Name | D4: D.K. Alluminum & Fiber | H4: Invoice No.
B5: Vendor Name | D5: Hasmukhbhai
B6: To, Tanvi Infracon - Pramukh Revanta | H6: Date - | I6: 45566
B7: Type of Work - | D7: Aluminium Window Fitting work | H7: Bill Date | I7: 45561
B8: Type of Contract - | D8: Aluminium Window Fitting work
B9: Payment Details
B10: Sr. No. | C10: Items | F10: % of Work Completed | G10: Qty | H10: Unit | I10: Rate/ Flat | J10: Amount
B11: 1 | C11: D- Building Window (109 to 1309) (13 Flats) | F11: 1 | G11: =265.75*13 -> 3454.75 | H11: Sq.ft. | I11: 195 | J11: =F11*I11*G11 -> 673676.25
B12: 2 | C12: D- Building Window (110 to 1310) (13 Flats) | F12: 1 | G12: =269.625*13 -> 3505.125 | H12: Sq.ft. | I12: 195 | J12: =F12*I12*G12 -> 683499.38
B13: 3 | C13: Passage Window (13 Floors) | F13: 1 | G13: =13*13 -> 169 | H13: Sq.ft. | I13: 195 | J13: =F13*I13*G13 -> 32955
B14: 4 | C14: Ventilation (109 to 1309) | F14: 1 | G14: =30.125*13 -> 391.625 | H14: Sq.ft. | I14: 250 | J14: =F14*I14*G14 -> 97906.25
B15: 5 | C15: Ventilation (110 to 1310) | F15: 1 | G15: =23.75*13 -> 308.75 | H15: Sq.ft. | I15: 250 | J15: =F15*I15*G15 -> 77187.5
C16: Total Bill Amount | J16: =SUM(J11:J15) -> 1565224.4 | L16: =J16+'2'!J16+'3'!J15 -> 3536412.9
C17: GST @ 18% | J17: 0
J19: =J16+J17+J18 -> 1565224.4
C20: Fifteen Lakh Sixty Five Thousand Two Hundred Twenty Four Only
C21: Advance Payment | J21: 0
C22: Retention @ 5% to be deducted | J22: 0
C23: Balance Payment to be paid | J23: =J19 -> 1565224.4
B25: TDS will be deducted as per applicable rules at your end
B30: Approved By -

Sheet 2
B2: Payment Certificate
B4: Company Name | D4: D.K. Alluminum & Fiber | H4: Invoice No.
B5: Vendor Name | D5: Hasmukhbhai
B6: To, Tanvi Infracon - Pramukh Revanta | H6: Date - | I6: 45572
B7: Type of Work - | D7: Aluminium Window Fitting work | H7: Bill Date | I7: 45571
B8: Type of Contract - | D8: Aluminium Window Fitting work
B9: Payment Details
B10: Sr. No. | C10: Items | F10: % of Work Completed | G10: Qty | H10: Unit | I10: Rate/ Flat | J10: Amount
B11: 1 | C11: E- Building Window (101 to 1311) (13 Flats) | F11: 1 | G11: =265.75*13 -> 3454.75 | H11: Sq.ft. | I11: 195 | J11: =F11*I11*G11 -> 673676.25
B12: 2 | C12: E- Building Window (102 to 1312) (13 Flats) | F12: 1 | G12: 3505 | H12: Sq.ft. | I12: 195 | J12: =F12*I12*G12 -> 683475
B13: 3 | C13: Passage Window (13 Floors) | F13: 1 | G13: 170 | H13: Sq.ft. | I13: 195 | J13: =F13*I13*G13 -> 33150
B14: 4 | C14: Ventilation (101 to 1311) | F14: 1 | G14: =30.08*13 -> 391.04 | H14: Sq.ft. | I14: 250 | J14: =F14*I14*G14 -> 97760
B15: 5 | C15: Ventilation (102 to 1312) | F15: 1 | G15: =23.75*13 -> 308.75 | H15: Sq.ft. | I15: 250 | J15: =F15*I15*G15 -> 77187.5
C16: Total Bill Amount | J16: =SUM(J11:J15) -> 1565248.8
C17: GST @ 18% | J17: 0
J19: =J16+J17+J18 -> 1565248.8
C20: Fifteen Lakh Sixty Five Thousand Two Hundred Fourty Nine Only
C21: Advance Payment | J21: 0
C22: Retention @ 5% to be deducted | J22: 0
C23: Balance Payment to be paid | J23: =J19 -> 1565248.8
B25: TDS will be deducted as per applicable rules at your end
B30: Approved By -

Sheet 3
B2: Payment Certificate
B4: Company Name | D4: D.K. Alluminum & Fiber | H4: Invoice No.
B5: Vendor Name | D5: Hasmukhbhai
B6: To, Tanvi Infracon - Pramukh Revanta | H6: Date - | I6: 45572
B7: Type of Work - | D7: Aluminium Window Fitting work | H7: Bill Date | I7: 45571
B8: Type of Contract - | D8: Aluminium Window Fitting work
B9: Payment Details
B10: Sr. No. | C10: Items | F10: % of Work Completed | G10: Qty | H10: Unit | I10: Rate/ Flat | J10: Amount
B11: 1 | C11: D- Building Passage Window Near Lift | F11: 1 | G11: =462+41.25 -> 503.25 | H11: Sq.ft. | I11: 195 | J11: =F11*I11*G11 -> 98133.75
B12: 2 | C12: D- Building Half Round Louvers Openable | F12: 1 | G12: =147.87+169 -> 316.87 | H12: Sq.ft. | I12: 300 | J12: =F12*I12*G12 -> 95061
B13: 3 | C13: E- Building Passage Window Near Lift | F13: 1 | G13: =423.5+82.5 -> 506 | H13: Sq.ft. | I13: 195 | J13: =F13*I13*G13 -> 98670 | L13: ='1'!J16+'2'!J16+'3'!J15 -> 3536412.9
B14: 4 | C14: E-Building Half Round Louvers Openable | F14: 1 | G14: =232.375+147.875 -> 380.25 | H14: Sq.ft. | I14: 300 | J14: =F14*I14*G14 -> 114075
C15: Total Bill Amount | J15: =SUM(J11:J14) -> 405939.75
C16: GST @ 18% | J16: 0
J18: =J15+J16+J17 -> 405939.75
C19: Four Lakh Five Thousand Nine Hundred Forty Only
C20: Advance Payment | J20: 0
C21: Retention @ 5% to be deducted | J21: 0
C22: Balance Payment to be paid | J22: =J18 -> 405939.75
B24: TDS will be deducted as per applicable rules at your end
B29: Approved By -

Sheet 4
B2: Payment Certificate
B4: Company Name | D4: D.K. Alluminum & Fiber | H4: Invoice No.
B5: Vendor Name | D5: Hasmukhbhai
B6: To, Tanvi Infracon - Pramukh Revanta | H6: Date - | I6: 45770
B7: Type of Work - | D7: Aluminium Window Fitting work | H7: Bill Date | I7: 45765
B8: Type of Contract - | D8: Aluminium Window Fitting work
B9: Payment Details
B10: Sr. No. | C10: Items | F10: % of Work Completed | G10: Qty | H10: Unit | I10: Rate/ Flat | J10: Amount
B11: 1 | C11: R40 A-Building | F11: 1 | G11: =21+15.75+17.5 -> 54.25 | H11: Sq.ft. | I11: 400 | J11: =F11*I11*G11 -> 21700
B12: 2 | C12: R40 B-Building | F12: 1 | G12: =16.5+13.5+30.875 -> 60.875 | H12: Sq.ft. | I12: 400 | J12: =F12*I12*G12 -> 24350
B13: 3 | C13: R40 C-Building | F13: 1 | G13: 15.625 | H13: Sq.ft. | I13: 400 | J13: =F13*I13*G13 -> 6250 | L13: ='1'!J16+'2'!J16+'4'!J16 -> 3236623.1
B14: 4 | C14: R40 D-Building | F14: 1 | G14: =15+13.5+37.375 -> 65.875 | H14: Sq.ft. | I14: 400 | J14: =F14*I14*G14 -> 26350
B15: 5 | C15: R40 E-Building | F15: 1 | G15: =18+15+35.75 -> 68.75 | H15: Sq.ft. | I15: 400 | J15: =F15*I15*G15 -> 27500
C16: Total Bill Amount | J16: =SUM(J11:J15) -> 106150
C17: GST @ 18% | J17: 0
J19: =J16+J17+J18 -> 106150
C20: One Lakh Six Thousand One Hundred Fifty Only
C21: Advance Payment | J21: 0
C22: Retention @ 5% to be deducted | J22: 0
C23: Balance Payment to be paid | J23: =J19 -> 106150
B25: TDS will be deducted as per applicable rules at your end
B30: Approved By -

Sheet 5
B2: Payment Certificate
B4: Company Name | D4: D.K. Alluminum & Fiber | H4: Invoice No.
B5: Vendor Name | D5: Hasmukhbhai
B6: To, Tanvi Infracon - Pramukh Revanta | H6: Date - | I6: 45770
B7: Type of Work - | D7: Aluminium Window Fitting work | H7: Bill Date | I7: 45765
B8: Type of Contract - | D8: Aluminium Window Fitting work
B9: Payment Details
B10: Sr. No. | C10: Items | F10: % of Work Completed | G10: Qty | H10: Unit | I10: Rate/ Flat | J10: Amount
B11: 1 | C11: B- Building Terrace Window and Duct Window (38 Nos.) | F11: 1 | G11: =195+173.33+20.25+24+9+8.25+11.25+12.25+173.33+238.33+20.25+24+9+9+11.25+12.1875 -> 950.6775 | H11: Sq.ft. | I11: 300 | J11: =F11*I11*G11 -> 285203.25
C12: Total Bill Amount | J12: =SUM(J11:J11) -> 285203.25
C13: GST @ 18% | J13: 0
J15: =J12+J13+J14 -> 285203.25
C16: Two Lakh Eighty Five Thousand Two Hundred Three Only
C17: Advance Payment | J17: 0
C18: Retention @ 5% to be deducted | J18: 0
C19: Balance Payment to be paid | J19: =J15 -> 285203.25
B21: TDS will be deducted as per applicable rules at your end
B26: Approved By -

Sheet 6
B2: Payment Certificate
B4: Company Name | D4: D.K. Alluminum & Fiber | H4: Invoice No.
B5: Vendor Name | D5: Hasmukhbhai
B6: To, Tanvi Infracon - Pramukh Revanta | H6: Date - | I6: 45770
B7: Type of Work - | D7: Aluminium Window Fitting work | H7: Bill Date | I7: 45765
B8: Type of Contract - | D8: Aluminium Window Fitting work
B9: Payment Details
B10: Sr. No. | C10: Items | F10: % of Work Completed | G10: Qty | H10: Unit | I10: Rate/ Flat | J10: Amount
B11: 1 | C11: C- Building Terrace Window and Duct Window (23 Nos.) | F11: 1 | G11: =19.47+19.25+17.5+19.7+21.5+19.25+19.25+19.7+8+16.875+15.625+15.625+15.625+16+15.625+16.25+16.25+16.25+15.625+15.625+15.625+15.625 -> 370.245 | H11: Sq.ft. | I11: 300 | J11: =F11*I11*G11 -> 111073.5
B12: 2 | C12: Lock | F12: 1 | G12: 2 | H12: Nos. | I12: 663 | J12: =F12*I12*G12 -> 1326
C13: Total Bill Amount | J13: =SUM(J11:J12) -> 112399.5
C14: GST @ 18% | J14: 0
J16: =J13+J14+J15 -> 112399.5
C17: Two Lakh Twelve Thousand Four Hundred Only
C18: Advance Payment | J18: 0
C19: Retention @ 5% to be deducted | J19: 0
C20: Balance Payment to be paid | J20: =J16 -> 112399.5
B22: TDS will be deducted as per applicable rules at your end
B27: Approved By -

Sheet 7
B2: Payment Certificate
B4: Company Name | D4: D.K. Alluminum & Fiber | H4: Invoice No.
B5: Vendor Name | D5: Hasmukhbhai
B6: To, Tanvi Infracon - Pramukh Revanta | H6: Date - | I6: 45771
B7: Type of Work - | D7: Aluminium Window Fitting work | H7: Bill Date | I7: 45765
B8: Type of Contract - | D8: Aluminium Window Fitting work
B9: Payment Details
B10: Sr. No. | C10: Items | F10: % of Work Completed | G10: Qty | H10: Unit | I10: Rate/ Flat | J10: Amount
B11: 1 | C11: C- Building 105 and 108 Window (26 Flats) | F11: 1 | G11: =(72.5+35+56.25+42.3+20.55+17.72)*26 -> 6352.32 | H11: Sq.ft. | I11: 195 | J11: =F11*I11*G11 -> 1238702.4
B12: 2 | C12: Toilet Ventilation work 105 and 108 Window (26 Flats) | F12: 1 | G12: =23.625*26 -> 614.25 | H12: Sq.ft. | I12: 250 | J12: =F12*I12*G12 -> 153562.5
B13: 3 | C13: C- Building 106 and 107 Window (26 Flats) | F13: 1 | G13: =237.5*26 -> 6175 | H13: Sq.ft. | I13: 195 | J13: =F13*I13*G13 -> 1204125
B14: 4 | C14: Toilet Ventilation work 106 and 107 Window (26 Flats) | F14: 1 | G14: =23.625*26 -> 614.25 | H14: Sq.ft. | I14: 250 | J14: =F14*I14*G14 -> 153562.5
C15: Total Bill Amount | J15: =SUM(J11:J14) -> 2749952.4
C16: GST @ 18% | J16: 0
J18: =J15+J16+J17 -> 2749952.4
C19: Twenty Seven Lakh Fourty Nine Thousand Nine Hundred Fifty Two Only
C20: Advance Payment | J20: 0
C21: Retention @ 5% to be deducted | J21: 0
C22: Balance Payment to be paid | J22: =J18 -> 2749952.4
B24: TDS will be deducted as per applicable rules at your end
B29: Approved By -

Sheet 8
B2: Payment Certificate
B4: Company Name | D4: D.K. Alluminum & Fiber | H4: Invoice No.
B5: Vendor Name | D5: Hasmukhbhai
B6: To, Tanvi Infracon - Pramukh Revanta | H6: Date - | I6: 45771
B7: Type of Work - | D7: Aluminium Window Fitting work | H7: Bill Date | I7: 45765
B8: Type of Contract - | D8: Aluminium Window Fitting work
B9: Payment Details
B10: Sr. No. | C10: Items | F10: % of Work Completed | G10: Qty | H10: Unit | I10: Rate/ Flat | J10: Amount
B11: 1 | C11: A- Building 101 Window (13 Flats) | F11: 1 | G11: =266*13 -> 3458 | H11: Sq.ft. | I11: 195 | J11: =F11*I11*G11 -> 674310
B12: 2 | C12: Toilet Ventilation work 104 Window (13 Flats) | F12: 1 | G12: =31*13 -> 403 | H12: Sq.ft. | I12: 250 | J12: =F12*I12*G12 -> 100750
B13: 3 | C13: A- Building 102 Window (13 Flats) | F13: 1 | G13: =270*13 -> 3510 | H13: Sq.ft. | I13: 195 | J13: =F13*I13*G13 -> 684450
B14: 4 | C14: Toilet Ventilation work 103 Window (13 Flats) | F14: 1 | G14: =25.325*13 -> 329.225 | H14: Sq.ft. | I14: 250 | J14: =F14*I14*G14 -> 82306.25
C15: Total Bill Amount | J15: =SUM(J11:J14) -> 1541816.2
C16: GST @ 18% | J16: 0
J18: =J15+J16+J17 -> 1541816.2
C19: Fifteen Lakh Fourty One Thousand Eight Hundred Sixteen Only
C20: Advance Payment | J20: 0
C21: Retention @ 5% to be deducted | J21: 0
C22: Balance Payment to be paid | J22: =J18 -> 1541816.2
B24: TDS will be deducted as per applicable rules at your end
B29: Approved By -

Sheet 9
B2: Payment Certificate
B4: Company Name | D4: D.K. Alluminum & Fiber | H4: Invoice No.
B5: Vendor Name | D5: Hasmukhbhai
B6: To, Tanvi Infracon - Pramukh Revanta | H6: Date - | I6: 45771
B7: Type of Work - | D7: Aluminium Window Fitting work | H7: Bill Date | I7: 45765
B8: Type of Contract - | D8: Aluminium Window Fitting work
B9: Payment Details
B10: Sr. No. | C10: Items | F10: % of Work Completed | G10: Qty | H10: Unit | I10: Rate/ Flat | J10: Amount
B11: 1 | C11: A- Building Passage Window (13 Floors) | F11: 1 | G11: =413.25+158.5+35.625 -> 607.375 | H11: Sq.ft. | I11: 195 | J11: =F11*I11*G11 -> 118438.12
B12: 2 | C12: B- Building Passage Window (13 Floors) | F12: 1 | G12: =413.25+158.5+35.625 -> 607.375 | H12: Sq.ft. | I12: 195 | J12: =F12*I12*G12 -> 118438.12
B13: 3 | C13: A- Building Lift Window | F13: 1 | G13: 6 | H13: Sq.ft. | I13: 300 | J13: =F13*I13*G13 -> 1800
B14: 4 | C14: B- Building Lift Window | F14: 1 | G14: 6 | H14: Sq.ft. | I14: 300 | J14: =F14*I14*G14 -> 1800
B15: 5 | C15: Handle with lock | F15: 1 | G15: 4 | H15: Sq.ft. | I15: 700 | J15: =F15*I15*G15 -> 2800
C16: Total Bill Amount | J16: =SUM(J11:J15) -> 243276.25
C17: GST @ 18% | J17: 0
J19: =J16+J17+J18 -> 243276.25
C20: Two Lakh Fourty Three Thousand Two Hundred Seventy Six Only
C21: Advance Payment | J21: 0
C22: Retention @ 5% to be deducted | J22: 0
C23: Balance Payment to be paid | J23: =J19 -> 243276.25
B25: TDS will be deducted as per applicable rules at your end
B30: Approved By -

Sheet 10
B2: Payment Certificate
B4: Company Name | D4: D.K. Alluminum & Fiber | H4: Invoice No.
B5: Vendor Name | D5: Hasmukhbhai
B6: To, Tanvi Infracon - Pramukh Revanta | H6: Date - | I6: 45771
B7: Type of Work - | D7: Aluminium Window Fitting work | H7: Bill Date | I7: 45765
B8: Type of Contract - | D8: Aluminium Window Fitting work
B9: Payment Details
B10: Sr. No. | C10: Items | F10: % of Work Completed | G10: Qty | H10: Unit | I10: Rate/ Flat | J10: Amount
B11: 1 | C11: B- Building 103 Window (13 Flats) | F11: 1 | G11: =263.8*13 -> 3429.4 | H11: Sq.ft. | I11: 195 | J11: =F11*I11*G11 -> 668733
B12: 2 | C12: Toilet Ventilation work 103 Window (13 Flats) | F12: 1 | G12: =29.75*13 -> 386.75 | H12: Sq.ft. | I12: 250 | J12: =F12*I12*G12 -> 96687.5
B13: 3 | C13: B- Building 104 Window (13 Flats) | F13: 1 | G13: =270.65*13 -> 3518.45 | H13: Sq.ft. | I13: 195 | J13: =F13*I13*G13 -> 686097.75
B14: 4 | C14: Toilet Ventilation work 104 Window (13 Flats) | F14: 1 | G14: =24.5*13 -> 318.5 | H14: Sq.ft. | I14: 250 | J14: =F14*I14*G14 -> 79625
C15: Total Bill Amount | J15: =SUM(J11:J14) -> 1531143.2 | L15: =J15+'9'!J19+'8'!J18+'7'!J15+'6'!J13+'5'!J12+'4'!J19+'3'!J15+'2'!J16+'1'!J16 -> 10106354
C16: GST @ 18% | J16: 0
J18: =J15+J16+J17 -> 1531143.2
C19: Fifteen Lakh Thirty One Thousand One Hundred Fourty Three Only
C20: Advance Payment | J20: 0
C21: Retention @ 5% to be deducted | J21: 0
C22: Balance Payment to be paid | J22: =J18 -> 1531143.2
B24: TDS will be deducted as per applicable rules at your end
B29: Approved By -

Sheet 11
B2: Payment Certificate
B4: Company Name | D4: D.K. Alluminum & Fiber | H4: Invoice No.
B5: Vendor Name | D5: Hasmukhbhai
B6: To, Tanvi Infracon - Pramukh Revanta | H6: Date - | I6: 45892
B7: Type of Work - | D7: Aluminium Window Fitting work | H7: Bill Date | I7: 45834
B8: Type of Contract - | D8: Aluminium Window Fitting work
B9: Payment Details
B10: Sr. No. | C10: Items | F10: % of Work Completed | G10: Qty | H10: Unit | I10: Rate/ Flat | J10: Amount
B11: 1 | C11: Security Cabin R-40 Door Tuffon Glass with Framing | F11: 1 | G11: 45 | H11: Sq.ft. | I11: 400 | J11: =F11*I11*G11 -> 18000
B12: 2 | C12: Tuffon Glass | F12: 1 | G12: 45 | H12: Sq.ft. | I12: 40 | J12: =F12*I12*G12 -> 1800
B13: 3 | C13: Tempo Rent for Door | F13: 1 | G13: 1 | H13: Lumsum | I13: 1200 | J13: =F13*I13*G13 -> 1200
B14: 4 | C14: A + B Building Gym Louvers | F14: 1 | G14: 56 | H14: Sq.ft. | I14: 300 | J14: =F14*I14*G14 -> 16800
B15: 5 | C15: D + E Building Social Club Louvers | F15: 1 | G15: 56 | H15: Sq.ft. | I15: 300 | J15: =F15*I15*G15 -> 16800
B16: 6 | C16: Tansformer Half Round Louvers | F16: 1 | G16: 152.875 | H16: Sq.ft. | I16: 300 | J16: =F16*I16*G16 -> 45862.5
B17: 7 | C17: E- Building Manager cabin toilet window | F17: 1 | G17: 1 | H17: Nos. | I17: 2000 | J17: =F17*I17*G17 -> 2000
B18: 8 | C18: B- Building Watchman area toilet window | F18: 1 | G18: 1 | H18: Nos. | I18: 2000 | J18: =F18*I18*G18 -> 2000
B19: 9 | C19: C- Building Basement Half round Opp. | F19: 1 | G19: 12.5 | H19: Sq.ft. | I19: 300 | J19: =F19*I19*G19 -> 3750
B20: 10 | C20: ST-167 Glass A,B,D and E | F20: 1 | G20: 1638 | H20: Sq.ft. | I20: 70 | J20: =F20*I20*G20 -> 114660
B21: 11 | C21: Carting Labour for 10, 11 and 12th Floor | F21: 1 | G21: 1638 | H21: Sq.ft. | I21: 10 | J21: =F21*I21*G21 -> 16380
B22: 12 | C22: Temp Rent for Glass | F22: 1 | G22: 1 | H22: Lumsum | I22: 2000 | J22: =F22*I22*G22 -> 2000
... B25: 15 | C25: Temp Rent for Window | F25: 1 | G25: 1 | H25: Lumsum | I25: 2000 | J25: =F25*I25*G25 -> 2000
C26: Total Bill Amount | J26: =SUM(J11:J25) -> 294552.5 | L26: =J26+'9'!J19+'8'!J18+'7'!J15+'6'!J13+'5'!J12+'4'!J19+'3'!J15+'2'!J16+'1'!J16+'10'!J18 -> 10400906
C27: GST @ 18% | J27: 0
J29: =J26+J27+J28 -> 294552.5
C30: Two Lakh Ninty Four Thousand Five Hundred Fifty Three Only
C31: Advance Payment | J31: 0
C32: Retention @ 5% to be deducted | J32: 0
C33: Balance Payment to be paid | J33: =J29 -> 294552.5
B35: TDS will be deducted as per applicable rules at your end
B40: Approved By -
