Workbook

Sheet 1
B2: Payment Certificate
B4: Company Name | D4: S M Construction | H4: Invoice No. | J4: 18
B5: Vendor Name | D5: Santosh Jadhav- 9902052488
B6: To, Tanvi Infracon - Revanta Project | H6: Date - | J6: 44627
B7: Type of Work - | D7: Guniting work | H7: Bill Date | J7: 44627
B8: Type of Contract - | D8: Guniting work with labour and part material
B9: Payment Details
B10: Sr. No. | C10: Items | F10: % of Work Completed | G10: Qty | H10: Unit | I10: Rate/ Flat | J10: Amount
B11: 1 | C11: Guniting work (Shortcrete) | F11: 1 | G11: 573.47 | H11: Sq.mt. | I11: 1150 | J11: =I11*G11 -> 659490.5 | M11: =G11+'2'!G11 -> 782.37
B12: 2 | C12: Nailing 3 Meter length | F12: 1 | G12: 247 | H12: Nos. | I12: 150 | J12: =I12*G12 -> 37050 | M12: =G12+'2'!G12 -> 374
B13: 3 | C13: Nailing 6 Meter length | F13: 1 | G13: 186 | H13: Nos. | I13: 300 | J13: =I13*G13 -> 55800 | M13: =G13 -> 186
B14: 4 | C14: V-poll | F14: 1 | G14: 18 | H14: Nos. | I14: 650 | J14: =I14*G14 -> 11700 | M14: =G14+'2'!G14 -> 116
C15: Total Bill Amount | J15: =SUM(J11:J14) -> 764040.5 | M15: ='2'!G13 -> 826
C16: GST @ 18% | J16: =J15*18% -> 137527.29
M17: =J18+'2'!J19+'3'!J19 -> 4417920.4
J18: =J15+J16+J17 -> 901567.79
C19: Nine lakh One thousand Five Hundred Sixty Eight Only
C20: Advance Payment | J20: 0
C21: Retention @ 5% to be deducted | J21: 0
C22: Balance Payment to be paid | J22: =J18 -> 901567.79
B24: TDS will be deducted as per applicable rules at your end
B29: Approved By -

Sheet 2
B2: Payment Certificate
B4: Company Name | D4: S M Construction | H4: Invoice No. | J4: 1
B5: Vendor Name | D5: Santosh Jadhav- 9902052488
B6: To, Tanvi Infracon - Revanta Project | H6: Date - | J6: 44659
B7: Type of Work - | D7: Guniting work | H7: Bill Date | J7: 44659
B8: Type of Contract - | D8: Guniting work with labour and part material
B9: Payment Details
B10: Sr. No. | C10: Items | F10: % of Work Completed | G10: Qty | H10: Unit | I10: Rate/ Flat | J10: Amount
B11: 1 | C11: Guniting work (Shortcrete) | F11: 1 | G11: 208.9 | H11: Sq.mt. | I11: 1150 | J11: =I11*G11 -> 240235
B12: 2 | C12: Nailing 3 Meter length | F12: 1 | G12: 127 | H12: Nos. | I12: 150 | J12: =I12*G12 -> 19050
B13: 3 | C13: Anchoring | F13: 1 | G13: 826 | H13: Nos. | I13: 1050 | J13: =I13*G13 -> 867300
B14: 4 | C14: V-poll | F14: 1 | G14: 98 | H14: Nos. | I14: 650 | J14: =I14*G14 -> 63700
B15: 5 | C15: Fabrication work for Channel and Plate | F15: 1 | G15: 3929.52 | H15: Kg | I15: 28 | J15: =I15*G15 -> 110026.56
C16: Total Bill Amount | J16: =SUM(J11:J15) -> 1300311.6
C17: GST @ 18% | J17: =J16*18% -> 234056.08
J19: =J16+J17+J18 -> 1534367.6
C20: Fifteen Lakh Thirty Thousand Three Hundred Sixty Eight only
C21: Advance Payment | J21: 0
C22: Retention @ 5% to be deducted | J22: 0
C23: Balance Payment to be paid | J23: =J19 -> 1534367.6
B25: TDS will be deducted as per applicable rules at your end
B30: Approved By -

Sheet 3
B2: Payment Certificate
B4: Company Name | D4: S M Construction | H4: Invoice No. | J4: 11
B5: Vendor Name | D5: Santosh Jadhav- 9902052488
B6: To, Tanvi Infracon - Revanta Project | H6: Date - | J6: 44721
B7: Type of Work - | D7: Guniting work | H7: Bill Date | J7: 44721
B8: Type of Contract - | D8: Guniting work with labour and part material
B9: Payment Details
B10: Sr. No. | C10: Items | F10: % of Work Completed | G10: Qty | H10: Unit | I10: Rate/ Flat | J10: Amount
B11: 1 | C11: Guniting work (Shortcrete) | F11: 1 | G11: 622.86 | H11: Sq.mt. | I11: 1150 | J11: =I11*G11 -> 716289
B12: 2 | C12: Nailing 3 Meter length | F12: 1 | G12: 127 | H12: Nos. | I12: 150 | J12: =I12*G12 -> 19050
B13: 3 | C13: Anchoring | F13: 1 | G13: 806 | H13: Nos. | I13: 1050 | J13: =I13*G13 -> 846300
B14: 4 | C14: V-poll | F14: 1 | G14: 59 | H14: Nos. | I14: 650 | J14: =I14*G14 -> 38350
B15: 5 | C15: Fabrication work for Channel and Plate | F15: 1 | G15: 2745.7 | H15: Kg | I15: 28 | J15: =I15*G15 -> 76879.6
C16: Total Bill Amount | J16: =SUM(J11:J15) -> 1696868.6
C17: GST @ 18% | J17: =J16*18% -> 305436.35
C18: Debit | J18: 20320
J19: =J16+J17-J18 -> 1981984.9
C20: Ninteen Lakh Eighty One Thousand Nine Hundred Eighty Five Only
C21: Advance Payment | J21: 0
C22: Retention @ 5% to be deducted | J22: 0
C23: Balance Payment to be paid | J23: =J19 -> 1981984.9
B25: TDS will be deducted as per applicable rules at your end
B30: Approved By -
